kozmoml/__init__.py
kozmoml/batch_processing.py
kozmoml/batching/__init__.py
kozmoml/batching/adaptive.py
kozmoml/batching/hooks.py
kozmoml/batching/requests.py
kozmoml/batching/shape.py
kozmoml/cache/__init__.py
kozmoml/cache/cache.py
kozmoml/cache/local/__init__.py
kozmoml/cache/local/local.py
kozmoml/cli/__init__.py
kozmoml/cli/build.py
kozmoml/cli/constants.py
kozmoml/cli/init_project.py
kozmoml/cli/main.py
kozmoml/cli/serve.py
kozmoml/cloudevents.py
kozmoml/codecs/__init__.py
kozmoml/codecs/base.py
kozmoml/codecs/base64.py
kozmoml/codecs/datetime.py
kozmoml/codecs/decorator.py
kozmoml/codecs/errors.py
kozmoml/codecs/lists.py
kozmoml/codecs/numpy.py
kozmoml/codecs/pandas.py
kozmoml/codecs/string.py
kozmoml/codecs/utils.py
kozmoml/context.py
kozmoml/env.py
kozmoml/errors.py
kozmoml/grpc/__init__.py
kozmoml/grpc/converters.py
kozmoml/grpc/dataplane_pb2.py
kozmoml/grpc/dataplane_pb2.pyi
kozmoml/grpc/dataplane_pb2_grpc.py
kozmoml/grpc/interceptors.py
kozmoml/grpc/logging.py
kozmoml/grpc/model_repository.py
kozmoml/grpc/model_repository_pb2.py
kozmoml/grpc/model_repository_pb2.pyi
kozmoml/grpc/model_repository_pb2_grpc.py
kozmoml/grpc/server.py
kozmoml/grpc/servicers.py
kozmoml/grpc/utils.py
kozmoml/handlers/__init__.py
kozmoml/handlers/custom.py
kozmoml/handlers/dataplane.py
kozmoml/handlers/model_repository.py
kozmoml/kafka/__init__.py
kozmoml/kafka/errors.py
kozmoml/kafka/handlers.py
kozmoml/kafka/logging.py
kozmoml/kafka/message.py
kozmoml/kafka/server.py
kozmoml/logging.py
kozmoml/metrics/__init__.py
kozmoml/metrics/context.py
kozmoml/metrics/errors.py
kozmoml/metrics/logging.py
kozmoml/metrics/prometheus.py
kozmoml/metrics/registry.py
kozmoml/metrics/server.py
kozmoml/middleware.py
kozmoml/model.py
kozmoml/parallel/__init__.py
kozmoml/parallel/dispatcher.py
kozmoml/parallel/errors.py
kozmoml/parallel/logging.py
kozmoml/parallel/messages.py
kozmoml/parallel/model.py
kozmoml/parallel/pool.py
kozmoml/parallel/registry.py
kozmoml/parallel/utils.py
kozmoml-0.1.0.dist-info/LICENSE
kozmoml-0.1.0.dist-info/METADATA
kozmoml-0.1.0.dist-info/WHEEL
kozmoml-0.1.0.dist-info/entry_points.txt
kozmoml-0.1.0.dist-info/RECORD
